coffeehouse/__init__.py
coffeehouse/api.py
coffeehouse/exception.py
coffeehouse/lydia/__init__.py
coffeehouse/lydia/lydia_ai.py
coffeehouse/lydia/session.py
coffeehouse-2.2.4.dist-info/LICENSE
coffeehouse-2.2.4.dist-info/METADATA
coffeehouse-2.2.4.dist-info/WHEEL
coffeehouse-2.2.4.dist-info/top_level.txt
coffeehouse-2.2.4.dist-info/RECORD
