Metadata-Version: 2.1
Name: coffeehouse
Version: 2.2.4
Summary: Official CoffeeHouse API Wrapper for Python
Home-page: https://coffeehouse.intellivoid.net/
Author: Intellivoid Technologies
Author-email: netkas@intellivoid.net
License: UNKNOWN
Platform: UNKNOWN
